md_convertor/__init__.py
md_convertor/__main__.py
md_convertor/convertor.py
md_convertor-2.0.0.dist-info/licenses/LICENSE
md_convertor-2.0.0.dist-info/METADATA
md_convertor-2.0.0.dist-info/WHEEL
md_convertor-2.0.0.dist-info/entry_points.txt
md_convertor-2.0.0.dist-info/top_level.txt
md_convertor-2.0.0.dist-info/RECORD
