Metadata-Version: 2.4
Name: md_convertor
Version: 2.0.0
Summary: Convert markdown file to html or pdf format
Author-email: Pengfei <liu.pengfei@hotmail.fr>
License:                     GNU GENERAL PUBLIC LICENSE
Project-URL: repository, https://github.com/pengfei99/MarkdownConvertor
Project-URL: documentation, https://github.com/pengfei99/MarkdownConvertor#
Keywords: markdown,html,pdf,convertor
Classifier: License :: OSI Approved :: MIT License
Classifier: Programming Language :: Python
Classifier: Programming Language :: Python :: 3
Requires-Python: >=3.9
License-File: LICENSE
Requires-Dist: weasyprint
Requires-Dist: markdown
Requires-Dist: click
Requires-Dist: pygments
Provides-Extra: build
Requires-Dist: build; extra == "build"
Requires-Dist: twine; extra == "build"
Provides-Extra: dev
Requires-Dist: black; extra == "dev"
Requires-Dist: bumpver; extra == "dev"
Requires-Dist: isort; extra == "dev"
Requires-Dist: mypy; extra == "dev"
Requires-Dist: pytest; extra == "dev"
Dynamic: license-file
